strands_agent_mcp/__init__.py
strands_agent_mcp/registry.py
strands_agent_mcp/server.py
strands_agent_mcp-0.1.0.dist-info/METADATA
strands_agent_mcp-0.1.0.dist-info/WHEEL
strands_agent_mcp-0.1.0.dist-info/entry_points.txt
strands_agent_mcp-0.1.0.dist-info/licenses/LICENSE
strands_agent_mcp-0.1.0.dist-info/RECORD
