Metadata-Version: 2.4
Name: strands-agent-mcp
Version: 0.1.0
Summary: MCP for executing strands agents
License-File: LICENSE
Classifier: Development Status :: 3 - Alpha
Classifier: Intended Audience :: Developers
Classifier: Intended Audience :: Science/Research
Classifier: License :: OSI Approved :: MIT License
Classifier: Operating System :: OS Independent
Classifier: Programming Language :: Python :: 3
Classifier: Topic :: Scientific/Engineering :: Artificial Intelligence
Classifier: Topic :: Software Development :: Libraries :: Python Modules
Requires-Python: >=3.10
Requires-Dist: fastmcp>=2.3.4
Requires-Dist: strands-agents-builder>=0.1.0
Requires-Dist: strands-agents-tools>=0.1.0
Requires-Dist: strands-agents>=0.1.1
